{
  "sources": [
    {
      "title": "はてなブックマーク - 人気エントリー - 総合",
      "feedUrl": "https://b.hatena.ne.jp/hotentry.rss",
      "siteUrl": "https://b.hatena.ne.jp/hotentry/all",
      "articles": [
        {
          "id": "https://www.buzzfeed.com/jp/naokoiwanaga/covid-19-nishiura-20210706-2",
          "author": null,
          "description": "国際的なサッカー選手権で見えた答え合わせ　専門家が命を守るために提示する3つの選択肢東京五輪を目前とした6月、国際的なサッカー選手権で大規模なクラスターが発生しました。このままいけば過去最大規模の感染爆発も考えられる中、新型コロナのデータ分析をしてきた西浦博さんは命を守るために3つの選択肢を提示しま...",
          "link": "https://www.buzzfeed.com/jp/naokoiwanaga/covid-19-nishiura-20210706-2",
          "publishedOn": "2021-07-08T00:12:43.000Z",
          "wordCount": 113,
          "title": "国際的なサッカー選手権で見えた答え合わせ　専門家が命を守るために提示する3つの選択肢"
        },
        {
          "id": "https://www.itmedia.co.jp/news/articles/2107/08/news041.html",
          "author": null,
          "description": "しばしば聴かれる質問。だが、この問題については誰もちゃんと答えていないようなので、西田宗千佳さんが乗り出した。 現在のスマートフォンは、ほとんどがバッテリー内蔵で、交換することができない。先日、「交換できないのは問題だ」とする記事がSNSでバズっていた。メーカーがスマホを買い替えさせるために交換でき...",
          "link": "https://www.itmedia.co.jp/news/articles/2107/08/news041.html",
          "publishedOn": "2021-07-07T23:19:10.000Z",
          "wordCount": 152,
          "title": "「なぜスマホのバッテリーは交換できないの？」　その理由と問題の本質を考える（1/4 ページ） - ITmedia NEWS"
        },
        {
          "id": "https://anond.hatelabo.jp/20210707182239",
          "author": null,
          "description": "笹？",
          "link": "https://anond.hatelabo.jp/20210707182239",
          "publishedOn": "2021-07-07T23:11:16.000Z",
          "wordCount": 105,
          "title": "七夕って何食べるんだっけ？"
        },
        {
          "id": "https://forest.watch.impress.co.jp/docs/special/1335793.html",
          "author": null,
          "description": "ゲーム業界やVTuber界隈で、3DCG制作ツール「Blender」に注目が集まっている。",
          "link": "https://forest.watch.impress.co.jp/docs/special/1335793.html",
          "publishedOn": "2021-07-07T22:01:09.000Z",
          "wordCount": 187,
          "title": "無償モデリングソフト「Blender」はVTuberで需要急増？大人気の「無償マニュアル」の裏側を聞いてみた - 窓の杜"
        },
        {
          "id": "https://www3.nhk.or.jp/news/html/20210708/k10013126071000.html",
          "author": null,
          "description": "大リーグ、エンジェルスの大谷翔平選手が今シーズン32号ホームランを打ち、大リーグでの日本選手のシーズン最多ホームラン記録を更新しました。 大谷選手は、前日の試合でピッチャーとして登板し日米通算50勝目をあげた翌日の7日も本拠地のカリフォルニア州アナハイムで行われているレッドソックス戦に2番 指名打者で先...",
          "link": "https://www3.nhk.or.jp/news/html/20210708/k10013126071000.html",
          "publishedOn": "2021-07-07T21:58:36.000Z",
          "wordCount": 32,
          "title": "大リーグ 大谷翔平 32号ホームラン 日本選手シーズン単独最多 | 大リーグ | NHKニュース"
        },
        {
          "id": "https://www3.nhk.or.jp/news/html/20210708/k10013125591000.html",
          "author": null,
          "description": "ファイザーの新型コロナウイルスのワクチンについて、厚生労働省は最大で3800万回分余りが、在庫として全国の医療機関などに保管されている可能性があるとして、自治体に活用するよう求めています。 一方、自治体からは2回目の接種のために確保している分などもあり、余っているワクチンは限られているという声が相次い...",
          "link": "https://www3.nhk.or.jp/news/html/20210708/k10013125591000.html",
          "publishedOn": "2021-07-07T21:08:29.000Z",
          "wordCount": 25,
          "title": "ファイザーのワクチン 医療機関など3800万回分余 在庫の可能性 | 新型コロナ ワクチン（日本国内） | NHKニュース"
        },
        {
          "id": "https://note.com/gotch_akg/n/nd5f787e9316c",
          "author": null,
          "description": "率直に言って、とても残念だ。ほとんど空白とも言える2020年を経て、また、大きな緊張を抱えて臨んだゴールデンウィークのフェスを乗り越えて、少しずつコロナ禍の先に新しい日常を見出すための、はじまりの季節だと、この夏を捉えていた。 当時の逡巡についてはこちらの投稿を読んでほしい。音楽関係者の困惑や憤り、そ...",
          "link": "https://note.com/gotch_akg/n/nd5f787e9316c",
          "publishedOn": "2021-07-07T17:36:10.000Z",
          "wordCount": 80,
          "title": "わきまえていないのは #4-3｜Masafumi Gotoh｜note"
        },
        {
          "id": "https://twitter.com/renho_sha/status/1412475495560581122",
          "author": null,
          "description": "いや、これ。 スパコンの使い方間違ってませんか。　 今までの映画館や劇場、イベント等の自粛や中止要請から一転、五輪は10000人でも大丈夫とのお墨付きに使うの、と思えてしまいます。 マスク着用で…観客1万人でも感染リスクゼロの… https://t.co/hOzAGAz6Df",
          "link": "https://twitter.com/renho_sha/status/1412475495560581122",
          "publishedOn": "2021-07-07T16:40:53.000Z",
          "wordCount": 196,
          "title": "蓮舫🙋‍♀️7/4都議選・立憲民主党 on Twitter: \"いや、これ。 スパコンの使い方間違ってませんか。　 今までの映画館や劇場、イベント等の自粛や中止要請から一転、五輪は10000人でも大丈夫とのお墨付きに使うの、と思えてしまいます。 マスク着用で…観客1万人でも感染リスクゼロの… https://t.co/hOzAGAz6Df\""
        },
        {
          "id": "https://www.wasteofpops.com/entry/2021/07/07/000000",
          "author": null,
          "description": "昨日の「マツコの知らない世界」で、SHOW-YAの寺田恵子さんと、Mary's Blood/NEMOPHILAのSAKIさんを迎えて「ガールズバンド」を特集していたのでぼんやりと眺めていたところ、いろいろ思いついたのでちょいちょいTwitterに流していたのですが、いったんまとめてみようと思いまして、書きます。 まず冒頭ですごく違和感を...",
          "link": "https://www.wasteofpops.com/entry/2021/07/07/000000",
          "publishedOn": "2021-07-07T16:40:35.000Z",
          "wordCount": 139,
          "title": "「ガールズバンド」のこと - WASTE OF POPS 80s-90s"
        },
        {
          "id": "https://anond.hatelabo.jp/20210707231116",
          "author": null,
          "description": "licensenecessaryreceive",
          "link": "https://anond.hatelabo.jp/20210707231116",
          "publishedOn": "2021-07-07T14:42:04.000Z",
          "wordCount": 79,
          "title": "いまだに綴りが覚えられない英単語"
        },
        {
          "id": "https://www.tokyo-np.co.jp/article/115235",
          "author": null,
          "description": "生活保護を申請した人らが公的支援で一時的に滞在するホテルから「五輪需要」を理由に退室を求められているとして、生活困窮者を支援する１０の団体などが７日、東京五輪・パラリンピック中に居場所を失う困窮者が出ないよう、都に実態把握や改善を求める要望書を提出した。 住まいがない生活保護申請者は、無料・低額宿...",
          "link": "https://www.tokyo-np.co.jp/article/115235",
          "publishedOn": "2021-07-07T14:33:45.000Z",
          "wordCount": 312,
          "title": "ホテル一時滞在の生活困窮者、五輪理由に退室迫られ...支援団体「居室確保を」と都に要望：東京新聞 TOKYO Web"
        },
        {
          "id": "https://anond.hatelabo.jp/20210707223409",
          "author": null,
          "description": "戦力差が10倍以上のもののみ取り上げています。随時更新中 古代・テルモピレーの戦い B.C.480　ペルシア戦争　ギリシア軍700vsペルシア軍30万以下 スパルタ王レオニダス指揮下のギリシア連合軍がペルシア軍の大軍と激突した。狭い地形を活かし、3日間の激戦を繰り広げるが、背後から攻撃され敗北した。この戦いでギリシ...",
          "link": "https://anond.hatelabo.jp/20210707223409",
          "publishedOn": "2021-07-07T13:36:31.000Z",
          "wordCount": 349,
          "title": "圧倒的な戦力差にも関わらず勝利・善戦した戦い"
        },
        {
          "id": "https://anond.hatelabo.jp/20210707163051",
          "author": null,
          "description": "新卒で入った会社の転勤で東京に来た。 もともと東京で働きたかったわけじゃない、でも若手で期待されているのを知ってたしキャリアアップになると確信して部署異動も含めて辞令を飲んだ、後悔はしてない。 でも転勤して、上司の期待通りのことは何一つ出来なくて、オペレーター仕事しかできず、なんのために転勤したの...",
          "link": "https://anond.hatelabo.jp/20210707163051",
          "publishedOn": "2021-07-07T13:25:40.000Z",
          "wordCount": 180,
          "title": "さよなら東京"
        },
        {
          "id": "https://www.j-cast.com/2021/07/07415629.html?p=all",
          "author": null,
          "description": "土石流で大きな被害を受けた静岡県熱海市は2021年7月7日、寄せられる支援物資の受け入れを一時休止すると発表した。 市の観光建設部の担当者は「心苦しい」と吐露する。なぜ、苦渋の決断となったのか。背景には送り手が思う「必要そうなもの」と「実際に必要なもの」とのギャップがあった。 「食事の提供も、飲料の提供...",
          "link": "https://www.j-cast.com/2021/07/07415629.html?p=all",
          "publishedOn": "2021-07-07T13:19:34.000Z",
          "wordCount": 171,
          "title": "支援物資いりません...熱海市が「苦渋の決断」　背景には何が？市が明かす被災地の現状: J-CAST ニュース【全文表示】"
        },
        {
          "id": "https://twitter.com/sekkai/status/1412727525906608133",
          "author": null,
          "description": "Pfizer の mRNA ワクチンの治験が4万人規模で圧倒的な成績を示しているのに、塩野義のワクチンが phase 2 trial の時点でたかだか200人でしか治験してなくて、それで年末までに緊急使用申請して6,000万人に投… https://t.co/7Vi1flwoiP",
          "link": "https://twitter.com/sekkai/status/1412727525906608133",
          "publishedOn": "2021-07-07T13:13:03.000Z",
          "wordCount": 196,
          "title": "sekkai on Twitter: \"Pfizer の mRNA ワクチンの治験が4万人規模で圧倒的な成績を示しているのに、塩野義のワクチンが phase 2 trial の時点でたかだか200人でしか治験してなくて、それで年末までに緊急使用申請して6,000万人に投… https://t.co/7Vi1flwoiP\""
        },
        {
          "id": "https://twitter.com/lady_merrow/status/1410192776671612930",
          "author": null,
          "description": "コロナ対策とマスク差止めをお願いしに10数名の市民が集まってノーマスクで 札幌市役所に出向いたら とても高圧的な態度をとられた挙句『ノーマスクの団体が騒いでいる』←（全く騒いでおらず真摯にお願いに行ったのに💦）と、警察を呼ばれ、意見を聞き入れようどせずにあちこちたらい回しにされ",
          "link": "https://twitter.com/lady_merrow/status/1410192776671612930",
          "publishedOn": "2021-07-07T13:10:24.000Z",
          "wordCount": 196,
          "title": "mipopo ariel on Twitter: \"コロナ対策とマスク差止めをお願いしに10数名の市民が集まってノーマスクで 札幌市役所に出向いたら とても高圧的な態度をとられた挙句『ノーマスクの団体が騒いでいる』←（全く騒いでおらず真摯にお願いに行ったのに💦）と、警察を呼ばれ、意見を聞き入れようどせずにあちこちたらい回しにされ\""
        },
        {
          "id": "https://twitter.com/Nou_YunYun/status/1412595306823180291",
          "author": null,
          "description": "ファイザー製ワクチンの供給管理表が不開示になったでござる https://t.co/BO8jCL3lkm",
          "link": "https://twitter.com/Nou_YunYun/status/1412595306823180291",
          "publishedOn": "2021-07-07T13:10:20.000Z",
          "wordCount": 196,
          "title": "電脳藻屑 on Twitter: \"ファイザー製ワクチンの供給管理表が不開示になったでござる https://t.co/BO8jCL3lkm\""
        },
        {
          "id": "https://mainichi.jp/articles/20210707/k00/00m/040/298000c",
          "author": null,
          "description": "北海道新聞の女性記者（22）が取材の際、国立大学法人旭川医科大（北海道旭川市）の建物内に無断で侵入したとして建造物侵入容疑で現行犯逮捕された事件で、同社は7日、経緯や見解をまとめた「社内調査報告」を公表した。この調査報告について、北海道新聞の元記者で、北海道警裏金問題の取材班代表として新聞協会賞など...",
          "link": "https://mainichi.jp/articles/20210707/k00/00m/040/298000c",
          "publishedOn": "2021-07-07T13:03:52.000Z",
          "wordCount": 484,
          "title": "北海道新聞は「調査報告の体をなしていない」元記者の識者が批判 | 毎日新聞"
        },
        {
          "id": "https://speakerdeck.com/yoshikiiida/readable-code-by-ddd",
          "author": null,
          "description": "Transcript モデリングを起点に可読性の高いコードを実現する 2021/07/07 #readablelt Yoshiki Iida リーダブルコード by DDD Yoshiki Iida (@ysk_118) エンジニアに始まり、スクラムマスター、プロダクトオーナー、マネージャー、執行 役員を経験し、現場のチームビルディングから部署を超えた会社全体の改善な ど、ア...",
          "link": "https://speakerdeck.com/yoshikiiida/readable-code-by-ddd",
          "publishedOn": "2021-07-07T12:53:34.000Z",
          "wordCount": 865,
          "title": "リーダブルコード by DDD / Readable Code by DDD - Speaker Deck"
        },
        {
          "id": "https://anond.hatelabo.jp/20210707213629",
          "author": null,
          "description": "手芸は「呪い」を解く？ 男子高校生が編み物を通して自分を取り戻す漫画「ニッターズハイ！」作者に聞く 「男が手芸なんて変だし」。自分にかけられてしまった「呪い」やジェンダーバイアスを解体していく物語『ニッターズハイ！ 』。「男子高校生が編み物をする」というテーマはどのようにして生まれたのか。作者の猫田...",
          "link": "https://anond.hatelabo.jp/20210707213629",
          "publishedOn": "2021-07-07T12:45:22.000Z",
          "wordCount": 1007,
          "title": "男性の問題について何故女性が首を突っ込んでくるのか？という疑問"
        },
        {
          "id": "https://jisin.jp/domestic/1998241/",
          "author": null,
          "description": "8月7～9日、14、15日に茨城県ひたちなか市・国営ひたち海浜公園で実施予定だった野外音楽フェス『ROCK IN JAPAN FESTIVAL 2021』の開催中止が、7月7日に発表された。 公式サイトによると、会場である国営ひたち海浜公園や地元自治体の茨城県、ひたちなか市と協議を重ねて開催の承認を得ていたというが、7月2日に茨城県医...",
          "link": "https://jisin.jp/domestic/1998241/",
          "publishedOn": "2021-07-07T12:32:09.000Z",
          "wordCount": 219,
          "title": "ロッキンに中止要請の県医師会「五輪は要請出す案件ではない」 | 女性自身"
        },
        {
          "id": "https://news.yahoo.co.jp/articles/ed108366d2f4c8248f916f6cc9b6961e25682d7a",
          "author": null,
          "description": "「当店は選手村なので堂々とお酒を提供します」。東京都内の飲食店が掲出した、こんな貼り紙がツイッターで話題になっている。 【写真】政治家への皮肉を効かせたポップも 赤、青、黄、緑と五輪マークのような色が付いた円弧に挟まれて、「IOC」と黒の字が入っている。国際オリンピック委員会の略称でもあるが、貼り紙で...",
          "link": "https://news.yahoo.co.jp/articles/ed108366d2f4c8248f916f6cc9b6961e25682d7a",
          "publishedOn": "2021-07-07T12:23:27.000Z",
          "wordCount": 86,
          "title": "「当店は選手村なので酒を提供します」　IOCに強烈皮肉？渋谷の居酒屋の貼り紙が話題に（J-CASTニュース） - Yahoo!ニュース"
        },
        {
          "id": "https://nordot.app/785443973644681216",
          "author": null,
          "description": "自民党各派閥は次期衆院選をにらみ、選挙準備を加速させている。竹下派は7日、東京都内の派閥事務所に選挙基盤の弱い若手や中堅議員を呼び出し、議席死守に向けた選挙運動の在り方を指南した。各派事務総長は党本部で会談し、不調に終わった都議選の結果を踏まえ、結束を再確認した。岸田派と石破派は8日に都内で政治資...",
          "link": "https://nordot.app/785443973644681216",
          "publishedOn": "2021-07-07T12:15:34.000Z",
          "wordCount": 37,
          "title": "自民、衆院選へ準備加速　若手指南、パーティー開催 ｜ 共同通信"
        },
        {
          "id": "https://dev.classmethod.jp/articles/technical-support-tips/",
          "author": null,
          "description": "AWS テクニカルサポートを 5 年経験して アノテーションの荒川です。 クラスメソッドメンバーズをご契約いただいているお客様のテクニカルサポート業務を始めて、早 5 年が経過しました。 私が対応したチケット件数をざっくりと調べたところ、本日時点で 1685 件でした。 最近は私がチケット対応する機会は減りまして、...",
          "link": "https://dev.classmethod.jp/articles/technical-support-tips/",
          "publishedOn": "2021-07-07T12:08:39.000Z",
          "wordCount": 339,
          "title": "AWS テクニカルサポートで得た暗黙知をまとめてみた | DevelopersIO"
        },
        {
          "id": "https://www.tokyo-np.co.jp/article/115209",
          "author": null,
          "description": "麻生太郎財務大臣は７日、財務省での会見で、学校法人「森友学園」に関する決裁文書を財務省が改ざんした問題について、改めて再調査を否定した。検察の調査を受けたことを理由に、「検察ですから第三者ですからね」と強調。質問した本紙記者を見つめ、「わかってるね？その部分。きょとんとしてるけど、それは顔のせい...",
          "link": "https://www.tokyo-np.co.jp/article/115209",
          "publishedOn": "2021-07-07T11:32:05.000Z",
          "wordCount": 321,
          "title": "麻生氏　森友改ざん「再調査しない」　本紙記者に「わかってるね？」容姿にまた言及：東京新聞 TOKYO Web"
        },
        {
          "id": "https://kaede2020.hatenablog.com/entry/2021/07/07/134334",
          "author": null,
          "description": "0.はじめに 1.簡単な自己紹介 2.年をとるにつれて衰える能力 3.低下した記憶力で競プロに取り組む 4.AtCoderのレベル感 5.競プロ上達への道のり 6.競プロとの向き合い方 7.競プロの依存性 8.競プロのコミュニティ 7.これから 8.終わりに 9.＜番外編＞もし後悔があるとすれば 0.はじめに こんにちは。競プロ歴一年半のか...",
          "link": "https://kaede2020.hatenablog.com/entry/2021/07/07/134334",
          "publishedOn": "2021-07-07T11:27:26.000Z",
          "wordCount": 166,
          "title": "40代で競プロができるのかという話 - 競プロ始めました"
        },
        {
          "id": "https://gigazine.net/news/20210707-robot-run-grocery-store/",
          "author": null,
          "description": "チャンネル登録者数397万人超の人気YouTuberであるトム・スコット氏が、イギリスのネットスーパーである「Ocado」の食料品倉庫に潜入し、その中で稼働する無数のロボットを紹介するムービーを公開し、話題を呼んでいます。 How many robots does it take to run a grocery store? - YouTube スコット氏がやってきたのは...",
          "link": "https://gigazine.net/news/20210707-robot-run-grocery-store/",
          "publishedOn": "2021-07-07T11:05:59.000Z",
          "wordCount": 194,
          "title": "2000台超のロボットが走り回ってネット通販で注文された商品をまとめて梱包する自動化された最新倉庫の実態を収めたムービー - GIGAZINE"
        },
        {
          "id": "https://anond.hatelabo.jp/20210707162046",
          "author": null,
          "description": "仁義なきプリキュア https://www.nishinippon.co.jp/item/n/765758/ というパワータイトルが出たので、これをこえるのを目指そう。 七人のプリキュア プリキュア家の一族 極道のプリキュアたち プリキュアの異常な愛情 ほかには？",
          "link": "https://anond.hatelabo.jp/20210707162046",
          "publishedOn": "2021-07-07T11:04:33.000Z",
          "wordCount": 405,
          "title": "映画のタイトルにプリキュア入れていこうぜ"
        },
        {
          "id": "https://www3.nhk.or.jp/news/html/20210707/k10013125451000.html",
          "author": null,
          "description": "新型コロナウイルス対策で、政府は、東京都を対象に4回目となる緊急事態宣言を出す方針を固め、与党側に伝えました。 沖縄県の緊急事態宣言も延長し、期限は、いずれも来月22日までとする方針です。 沖縄も延長の方針 沖縄県を対象にした緊急事態宣言と、東京など10の都道府県に適用されているまん延防止等重点措置は、...",
          "link": "https://www3.nhk.or.jp/news/html/20210707/k10013125451000.html",
          "publishedOn": "2021-07-07T10:37:16.000Z",
          "wordCount": 30,
          "title": "東京に4回目の緊急事態宣言へ 期限来月22日まで 政府方針 | 新型コロナウイルス | NHKニュース"
        },
        {
          "id": "https://bunshun.jp/articles/-/46660",
          "author": null,
          "description": "平井氏が保有していたのは、IT関連企業「豆蔵ホールディングス」（東京都新宿区）の株式8400株。同社は、荻原紀男社長（63）が1999年に創業した会社が前身で、2004年に東証マザーズ、2013年に東証一部への上場を果たした。 最近では、豆蔵ホールディングスのグループ会社「ネクストスケープ」（東京都新宿区）が、内閣官...",
          "link": "https://bunshun.jp/articles/-/46660",
          "publishedOn": "2021-07-07T07:08:30.000Z",
          "wordCount": 202,
          "title": "平井デジタル相に資産公開法違反の疑い　“五輪アプリ受注”の親密ITグループの株を不記載 | 文春オンライン"
        }
      ]
    }
  ],
  "cliVersion": "1.11.0"
}